barn/__init__.py
barn/_version.py
barn/azure.py
barn/cfg.py
barn/dataset.py
barn/exceptions.py
barn-0.0.5.dist-info/METADATA
barn-0.0.5.dist-info/RECORD
barn-0.0.5.dist-info/WHEEL
barn-0.0.5.dist-info/top_level.txt
tests/__init__.py
tests/test_basics.py
tests/test_versioning.py
